AUTHORS
LICENSE
MANIFEST.in
README.md
README.ru.md
requirements-devel.txt
requirements.txt
setup.py
bash_completion.d/chewy
bin/chewy
bin/chewy-update-manifest
chewy/__init__.py
chewy/fancy_grid.py
chewy/manifest.py
chewy/meta.py
chewy/module.py
chewy/session.py
chewy/version.py
chewy.egg-info/PKG-INFO
chewy.egg-info/SOURCES.txt
chewy.egg-info/dependency_links.txt
chewy.egg-info/requires.txt
chewy.egg-info/top_level.txt
test/__init__.py
test/test_chewy.py
test/test_fancy_grid.py
test/test_manifest.py
test/test_meta.py
test/test_module.py
test/test_session.py
test/test_version.py