Metadata-Version: 1.1
Name: chewy
Version: 0.4
Summary: Python script to manage CMake modules
Home-page: https://github.com/mutanabbi/chewy
Author: Alex Turbov
Author-email: I.zaufi@gmail.com
License: GNU General Public License v3 or later (GPLv3+)
Download-URL: https://github.com/mutanabbi/chewy/archive/version-0.4.tar.gz
Keywords: CMake modules synchronizer
Platform: UNKNOWN
Classifier: Development Status :: 5 - Production/Stable
Classifier: Environment :: Console
Classifier: Intended Audience :: Developers
Classifier: License :: OSI Approved :: GNU General Public License v3 (GPLv3)
Classifier: Natural Language :: English
Classifier: Operating System :: POSIX :: Linux
Classifier: Programming Language :: Python
Classifier: Programming Language :: Python :: 3
Classifier: Topic :: Software Development :: Version Control
